lhub_integ/__init__.py
lhub_integ/bundle_requirements.py
lhub_integ/common/__init__.py
lhub_integ/common/constants.py
lhub_integ/common/email_helpers.py
lhub_integ/common/file_helpers.py
lhub_integ/common/file_manager_client.py
lhub_integ/common/helpers.py
lhub_integ/common/input_helpers.py
lhub_integ/common/input_json_helpers.py
lhub_integ/common/json_helpers.py
lhub_integ/common/override_default_socket_with_proxy.py
lhub_integ/common/query_parser.py
lhub_integ/common/request_helpers.py
lhub_integ/common/response_helpers.py
lhub_integ/common/time_between_rows_validate.py
lhub_integ/common/time_helpers.py
lhub_integ/common/url_maker.py
lhub_integ/common/validations.py
lhub_integ/common/verify_ssl.py
lhub_integ/decorators.py
lhub_integ/env.py
lhub_integ/execution.py
lhub_integ/generate_metadata.py
lhub_integ/params.py
lhub_integ/shim_exec.py
lhub_integ/shim_validate.py
lhub_integ/util.py
lhub_integ-1.0.14.dist-info/METADATA
lhub_integ-1.0.14.dist-info/WHEEL
lhub_integ-1.0.14.dist-info/entry_points.txt
lhub_integ-1.0.14.dist-info/RECORD
