Metadata-Version: 2.3
Name: lhub_integ
Version: 1.0.14
Summary: The Logichub Integration SDK
License: MIT
Keywords: security,automation,logichub
Author: Russell Cohen
Author-email: russell@logichub.com
Requires-Python: >=3.6,<4.0
Classifier: License :: OSI Approved :: MIT License
Classifier: Programming Language :: Python :: 3
Classifier: Programming Language :: Python :: 3.6
Classifier: Programming Language :: Python :: 3.7
Classifier: Programming Language :: Python :: 3.8
Classifier: Programming Language :: Python :: 3.9
Classifier: Programming Language :: Python :: 3.10
Classifier: Programming Language :: Python :: 3.11
Classifier: Programming Language :: Python :: 3.12
Classifier: Programming Language :: Python :: 3.13
Requires-Dist: Jinja2
Requires-Dist: PySocks (==1.7.1)
Requires-Dist: PyYAML
Requires-Dist: beautifulsoup4 (==4.8.2)
Requires-Dist: click (>=7.0,<7.1)
Requires-Dist: dataclasses-json
Requires-Dist: docstring-parser (>=0.1,<0.2)
Requires-Dist: netaddr (==0.7.19)
Requires-Dist: python-dateutil (==2.8.1)
Requires-Dist: python-magic (==0.4.15)
Requires-Dist: urllib3
Project-URL: Homepage, https://logichub.com
